notifier/__init__.py
notifier/_constants.py
notifier/_notifier.py
notifier/test.py
notifier/tests/__init__.py
notifier/tests/test_notifier.py
notifier-1.0.3.dist-info/top_level.txt
notifier-1.0.3.dist-info/METADATA
notifier-1.0.3.dist-info/pbr.json
notifier-1.0.3.dist-info/DESCRIPTION.rst
notifier-1.0.3.dist-info/metadata.json
notifier-1.0.3.dist-info/WHEEL
notifier-1.0.3.dist-info/RECORD
